escarpolette/__init__.py
escarpolette/__main__.py
escarpolette/admin/__init__.py
escarpolette/db.py
escarpolette/extensions.py
escarpolette/login.py
escarpolette/migrations/__init__.py
escarpolette/migrations/v001.sql
escarpolette/migrations/v002.sql
escarpolette/models/__init__.py
escarpolette/models/item.py
escarpolette/models/mixin.py
escarpolette/models/playlist.py
escarpolette/models/version.py
escarpolette/player.py
escarpolette/routers/__init__.py
escarpolette/routers/dependencies.py
escarpolette/routers/items.py
escarpolette/routers/player.py
escarpolette/rules/__init__.py
escarpolette/rules/limited.py
escarpolette/schemas/__init__.py
escarpolette/schemas/item.py
escarpolette/schemas/player.py
escarpolette/schemas/playlist.py
escarpolette/settings.py
escarpolette/tools.py
escarpolette-0.7.2.dist-info/entry_points.txt
escarpolette-0.7.2.dist-info/LICENSE
escarpolette-0.7.2.dist-info/WHEEL
escarpolette-0.7.2.dist-info/METADATA
escarpolette-0.7.2.dist-info/RECORD
