Metadata-Version: 2.1
Name: escarpolette
Version: 0.7.2
Summary: Manage your musical playlist with your friends without starting a war.
Home-page: https://github.com/erdnaxeli/escarpolette
License: GPL-3.0
Author: Alexandre Morignot
Author-email: erdnaxeli@cervoi.se
Requires-Python: >=3.7,<4.0
Classifier: License :: OSI Approved :: GNU General Public License v3 (GPLv3)
Classifier: Programming Language :: Python :: 3
Classifier: Programming Language :: Python :: 3.7
Classifier: Programming Language :: Python :: 3.8
Requires-Dist: click (>=7.0,<8.0)
Requires-Dist: fastapi (>=0.47.1,<0.48.0)
Requires-Dist: importlib_metadata (>=1.5.0,<2.0.0)
Requires-Dist: pydantic (>=1.3,<2.0)
Requires-Dist: pyjwt (>=1.7.1,<2.0.0)
Requires-Dist: sqlalchemy (>=1.2,<2.0)
Requires-Dist: uvicorn (>=0.11.2,<0.12.0)
Requires-Dist: xdg (>=4.0,<5.0)
Requires-Dist: youtube-dl
Project-URL: Repository, https://github.com/erdnaxeli/escarpolette.git
